tinylogging/__init__.py
tinylogging/aio/__init__.py
tinylogging/aio/handlers.py
tinylogging/formatter.py
tinylogging/helpers/__init__.py
tinylogging/level.py
tinylogging/py.typed
tinylogging/record.py
tinylogging/sync/__init__.py
tinylogging/sync/handlers.py
tinylogging-5.0.1.dist-info/LICENSE
tinylogging-5.0.1.dist-info/METADATA
tinylogging-5.0.1.dist-info/WHEEL
tinylogging-5.0.1.dist-info/RECORD
