Metadata-Version: 2.3
Name: tinylogging
Version: 5.0.1
Summary: python logging library
License: MIT
Keywords: logging
Author: Hamlet
Author-email: hamlets849@gmail.com
Requires-Python: >=3.9
Classifier: Development Status :: 5 - Production/Stable
Classifier: Intended Audience :: Developers
Classifier: License :: OSI Approved :: MIT License
Classifier: Programming Language :: Python
Classifier: Programming Language :: Python :: 3
Classifier: Operating System :: OS Independent
Classifier: Topic :: System :: Logging
Classifier: Typing :: Typed
Requires-Dist: anyio (>=4.6.2,<5.0.0)
Requires-Dist: colorama (>=0.4.6,<0.5.0)
Requires-Dist: httpx (>=0.28.1,<0.29.0)
Project-URL: Bug Tracker, https://github.com/HamletSargsyan/tinylogging/issues
Project-URL: Documentation, https://hamletsargsyan.github.io/tinylogging
Project-URL: Homepage, https://github.com/HamletSargsyan/tinylogging
Project-URL: Repository, https://github.com/HamletSargsyan/tinylogging
